Workbook

Sheet Assumptions
A1: ASSUMPTIONS — change anything BLUE
A2: Every other sheet reads from here. Blue = you type it. Black = calculated.
A4: INCOME
A5: Child Support — Aguayo (weekly, Tuesdays) | B5: 320 | C5: Stated by you
A6: State paycheck (every other Friday, net) | B6: 1100 | C6: Stated by you — net, not gross
A7: Child Support — Cartagena (Sept, every 2 wks) | B7: 500 | C7: Drops to $250 from October
A8: Child Support — Cartagena (Oct onward) | B8: 250 | C8: Your update
A9: MONTHLY BILLS
A10: Rent | B10: 2100 | C10: Stated by you
A11: Westlake Financial (due 17th) | B11: 580 | C11: Aug payment deferred to back of loan
A12: Daycare | B12: 300 | C12: Your estimate — confirm
A13: Loan Mart | B13: 240
A14: Light | B14: 200
A15: Spectrum | B15: 100
A16: Car storage | B16: 80
A17: Credit repair (mid-month draft) | B17: 70
A18: Living money per week | B18: 100 | C18: Gas, food, medicine. Not optional.
A19: DEBTS
A20: Mom's credit card balance | B20: 650 | C20: Your update — was $400
A21: Mom's card — September minimum | B21: 50 | C21: Payoff is October
A22: Cash advance owed | B22: 220
A23: Existing pawn — amount owed | B23: 320 | C23: Borrowed $250. ~25 days left as of Aug 28
A24: Necklace pawn — cash received | B24: 800
A25: Necklace return fee % | B25: 0.25 | C25: 40–45 day window; redemption ~Oct 7
A26: SIDE HUSTLE (Backup Fund)
A27: Plasma per month | B27: 200 | C27: Low bar on purpose
A28: DoorDash / Uber per month | B28: 200
A29: Process server per month (Oct onward) | B29: 200 | C29: License not through for September
A30: FLEX
A31: Flex payment 1 (due by the 4th) | B31: 1500 | C31: Stated by you
A32: AUGUST + EVICTION
A33: August rent target (incl. court/late fees) | B33: 2200 | C33: Rent $2,100 + expected court costs
A34: Court costs added after filing (estimate) | B34: 350 | C34: Filing fee + summons + service. CONFIRM with legal aid
A36: HOW TO USE THIS
A37: Blue text on yellow | B37: example | C37: You type here. Everything else recalculates from it.
A38: Green text | C38: Pulled from another sheet.
A39: Black text | C39: Calculated on this sheet.
A40: To print | C40: File > Print. Already set to landscape, one page wide.

Sheet Summary
A1: SUMMARY — the whole picture on one page
A2: Every number here is pulled live from the month tabs. Change anything on Assumptions and this updates.
B4: September | C4: October | D4: November | E4: December
A5: Opening balance | B5: =September!B29 -> 0 | C5: =October!B28 -> 440 | D5: =November!B26 -> 450 | E5: =December!B27 -> 960
A6: Money in | B6: =September!B30 -> 5200 | C6: =October!B29 -> 5680 | D6: =November!B27 -> 4580 | E6: =December!B28 -> 4900
A7: Money out | B7: =September!B31 -> 4760 | C7: =October!B30 -> 5670 | D7: =November!B28 -> 4070 | E7: =December!B29 -> 4470
A8: CLOSING BALANCE | B8: =September!B32 -> 440 | C8: =October!B31 -> 450 | D8: =November!B29 -> 960 | E8: =December!B30 -> 1390
A9: Added this month | B9: =September!B33 -> 440 | C9: =October!B32 -> 10 | D9: =November!B30 -> 510 | E9: =December!B31 -> 430
A10: Covers next rent alone? | B10: =September!B34 -> NO — short $1,660 | C10: =October!B33 -> NO — short $1,650 | D10: =November!B31 -> NO — short $1,140 | E10: =December!B32 -> NO — short $710
A11: If zero side hustle | B11: =September!B37 -> 40 | C11: =October!B36 -> -150 | D11: =November!B34 -> 360 | E11: =December!B35 -> 790
A13: THE FINISH LINE
A14: You are truly ahead the first month this balance can pay rent by itself before a single paycheck arrives.

Sheet Next 8 Days
A1: THE NEXT 8 DAYS — August rent + September rent
A2: You have been served. The court filing deadline (~Sept 5) matters MORE than the money.
A4: WHAT YOU NEED
A5: August rent (incl. expected court costs) | C5: =Assumptions!$B$33 -> 2200
A6: September rent — FULL amount | C6: =Assumptions!$B$10 -> 2100 | E6: Flex will NOT work while August is past due — September is the full amount, not $1,500
A7: TOTAL NEEDED | C7: =C5+C6 -> 4300
A9: EVERY DOLLAR, IN THE ORDER IT ARRIVES
A10: When | B10: What | C10: Amount | D10: Running total | E10: Notes
A11: Fri Aug 28 | B11: Child support card — on hand | C11: =Assumptions!$B$5*0+200 -> 200 | D11: =C11 -> 200 | E11: Already on the card
A12: Fri Aug 28 | B12: Plasma card balance | C12: =150 -> 150 | D12: =D11+C12 -> 350 | E12: Already banked
A13: Mon Aug 31 | B13: Child Support — Cartagena | C13: =Assumptions!$B$7 -> 500 | D13: =D12+C13 -> 850 | E13: The $500 that slipped to Monday
A14: Before Aug 31 | B14: Cash advance apps | C14: =Assumptions!$B$22 -> 220 | D14: =D13+C14 -> 1070 | E14: Borrowed — repay in September
A15: Before Aug 31 | B15: Plasma promo — remaining donations | C15: =250 -> 250 | D15: =D14+C15 -> 1320 | E15: YOU HAVE TO EARN THIS
A16: Before Aug 31 | B16: Necklace pawn | C16: =Assumptions!$B$24 -> 800 | D16: =D15+C16 -> 2120 | E16: Borrowed — redeem by ~Oct 7
A17: Tue Sep 1 | B17: Child Support — Aguayo | C17: =Assumptions!$B$5 -> 320 | D17: =D16+C17 -> 2440 | E17: Weekly
A18: Fri Sep 4 | B18: State Paycheck 1 | C18: =Assumptions!$B$6 -> 1100 | D18: =D17+C18 -> 3540 | E18: Flex deadline day
B19: TOTAL LANDING BY SEPT 4 | C19: =SUM(C11:C18) -> 3540
B20: GAP — still to find | C20: =MAX(0,C7-C19) -> 760 | D20: =IF(C20=0,"COVERED","= $"&TEXT(C20/8,"#,##0")&" per day for 8 days") -> = $95 per day for 8 days
A22: BEFORE YOU SPEND A DOLLAR
A23: Step 1 | B23: Call Community Legal Services of Mid-Florida (Osceola) Monday morning
A24: Step 2 | B24: Check the court docket for your address | E24: Confirm it is actually filed, not just threatened
A25: Step 3 | B25: File your written response with the court by ~Sept 5 | E25: MISS THIS AND YOU LOSE BY DEFAULT even holding every dollar
A26: Step 4 | B26: Ask the pawn shop about an interest-only extension | E26: Before you sign, not after
A27: Step 5 | B27: Tell the landlord the exact date the money lands | E27: A specific date beats silence
B29: NOTE: once filed, the landlord can refuse payment. To contest you generally deposit rent INTO THE COURT REGISTRY, not with the landlord.

Sheet September
A1: SEPTEMBER — MONEY IN vs MONEY OUT
A3: MONEY IN
A4: Child Support — Aguayo ×5 Tuesdays | B4: =Assumptions!$B$5*5 -> 1600 | D4: Guaranteed
A5: State paycheck ×2 | B5: =Assumptions!$B$6*2 -> 2200 | D5: Guaranteed
A6: Child Support — Cartagena ×2 | B6: =Assumptions!$B$7*2 -> 1000 | D6: Guaranteed
A7: Plasma | B7: =Assumptions!$B$27 -> 200 | D7: MUST BE EARNED
A8: DoorDash / Uber | B8: =Assumptions!$B$28 -> 200 | D8: MUST BE EARNED
A9: Process server | B9: =Assumptions!$B$29*0 -> 0 | D9: License not through yet — $0 for September
A10: GUARANTEED SUBTOTAL | B10: =SUM(B4:B6) -> 4800
A11: BACKUP FUND SUBTOTAL (earned) | B11: =SUM(B7:B9) -> 400
A13: MONEY OUT
A14: Rent | B14: =Assumptions!$B$10 -> 2100 | D14: Paid through Flex: $1,500 by the 4th, the rest by the 15th
A15: Westlake (due the 17th) | B15: =Assumptions!$B$11 -> 580 | D15: Your paycheck lands the 18th — ONE DAY LATE every month
A16: Daycare | B16: =Assumptions!$B$12 -> 300
A17: Loan Mart | B17: =Assumptions!$B$13 -> 240
A18: Light | B18: =Assumptions!$B$14 -> 200
A19: Spectrum | B19: =Assumptions!$B$15 -> 100 | D19: Safest bill to be late on
A20: Car storage | B20: =Assumptions!$B$16 -> 80
A21: Credit repair | B21: =Assumptions!$B$17 -> 70
A22: Living money ×5 weeks | B22: =Assumptions!$B$18*5 -> 500 | D22: Gas, food, medicine
A23: Existing pawn — CLEAR IT | B23: =Assumptions!$B$23 -> 320 | D23: Hard deadline ~Sep 19. No grace period on a pawn
A24: Cash advance repayment | B24: =Assumptions!$B$22 -> 220
A25: Mom's credit card — minimum | B25: =Assumptions!$B$21 -> 50 | D25: Payoff is October
A26: TOTAL OUT | B26: =SUM(B14:B25) -> 4760
A28: RENT SAVINGS ACCOUNT
A29: Opening balance | B29: 0 | D29: Last month's leftover. This is NOT spare money — it is next month's rent arriving early.
A30: + Money in (guaranteed + backup) | B30: =B10+B11 -> 5200
A31: − Money out (rent included) | B31: =B26 -> 4760
A32: CLOSING BALANCE | B32: =B29+B30-B31 -> 440 | D32: Carries into next month as the opening balance
A33: Added this month | B33: =B32-B29 -> 440
A34: Could this pay next month's rent alone? | B34: =IF(B32>=Assumptions!$B$10,"YES","NO — short $"&TEXT(Assumptions!$B$10-B32,"#,##0")) -> NO — short $1,660
A36: IF NO SIDE HUSTLE AT ALL
A37: Closing balance with $0 earned | B37: =B29+B10-B26 -> 40 | D37: The gap between this and the number above is exactly what the side work buys you.

Sheet October
A1: OCTOBER — MONEY IN vs MONEY OUT
A3: MONEY IN
A4: Child Support — Aguayo ×4 Tuesdays | B4: =Assumptions!$B$5*4 -> 1280 | D4: Guaranteed
A5: State paycheck ×3 | B5: =Assumptions!$B$6*3 -> 3300 | D5: Guaranteed — THREE paychecks this month
A6: Child Support — Cartagena ×2 | B6: =Assumptions!$B$8*2 -> 500 | D6: Guaranteed
A7: Plasma | B7: =Assumptions!$B$27 -> 200 | D7: MUST BE EARNED
A8: DoorDash / Uber | B8: =Assumptions!$B$28 -> 200 | D8: MUST BE EARNED
A9: Process server | B9: =Assumptions!$B$29*1 -> 200 | D9: MUST BE EARNED
A10: GUARANTEED SUBTOTAL | B10: =SUM(B4:B6) -> 5080
A11: BACKUP FUND SUBTOTAL (earned) | B11: =SUM(B7:B9) -> 600
A13: MONEY OUT
A14: Rent | B14: =Assumptions!$B$10 -> 2100 | D14: Paid through Flex: $1,500 by the 4th, the rest by the 15th
A15: Westlake (due the 17th) | B15: =Assumptions!$B$11 -> 580 | D15: Your paycheck lands the 18th — ONE DAY LATE every month
A16: Daycare | B16: =Assumptions!$B$12 -> 300
A17: Loan Mart | B17: =Assumptions!$B$13 -> 240
A18: Light | B18: =Assumptions!$B$14 -> 200
A19: Spectrum | B19: =Assumptions!$B$15 -> 100 | D19: Safest bill to be late on
A20: Car storage | B20: =Assumptions!$B$16 -> 80
A21: Credit repair | B21: =Assumptions!$B$17 -> 70
A22: Living money ×4 weeks | B22: =Assumptions!$B$18*4 -> 400 | D22: Gas, food, medicine
A23: Mom's credit card — PAY IT OFF | B23: =Assumptions!$B$20-Assumptions!$B$21 -> 600 | D23: Card is cleared this month
A24: Necklace redemption (if pawned) | B24: =Assumptions!$B$24*(1+Assumptions!$B$25) -> 1000 | D24: Due ~Oct 7. Set to 0 if you did not pawn
A25: TOTAL OUT | B25: =SUM(B14:B24) -> 5670
A27: RENT SAVINGS ACCOUNT
A28: Opening balance | B28: =September!B32 -> 440 | D28: Last month's leftover. This is NOT spare money — it is next month's rent arriving early.
A29: + Money in (guaranteed + backup) | B29: =B10+B11 -> 5680
A30: − Money out (rent included) | B30: =B25 -> 5670
A31: CLOSING BALANCE | B31: =B28+B29-B30 -> 450 | D31: Carries into next month as the opening balance
A32: Added this month | B32: =B31-B28 -> 10
A33: Could this pay next month's rent alone? | B33: =IF(B31>=Assumptions!$B$10,"YES","NO — short $"&TEXT(Assumptions!$B$10-B31,"#,##0")) -> NO — short $1,650
A35: IF NO SIDE HUSTLE AT ALL
A36: Closing balance with $0 earned | B36: =B28+B10-B25 -> -150 | D36: The gap between this and the number above is exactly what the side work buys you.

Sheet November
A1: NOVEMBER — MONEY IN vs MONEY OUT
A3: MONEY IN
A4: Child Support — Aguayo ×4 Tuesdays | B4: =Assumptions!$B$5*4 -> 1280 | D4: Guaranteed
A5: State paycheck ×2 | B5: =Assumptions!$B$6*2 -> 2200 | D5: Guaranteed
A6: Child Support — Cartagena ×2 | B6: =Assumptions!$B$8*2 -> 500 | D6: Guaranteed
A7: Plasma | B7: =Assumptions!$B$27 -> 200 | D7: MUST BE EARNED
A8: DoorDash / Uber | B8: =Assumptions!$B$28 -> 200 | D8: MUST BE EARNED
A9: Process server | B9: =Assumptions!$B$29*1 -> 200 | D9: MUST BE EARNED
A10: GUARANTEED SUBTOTAL | B10: =SUM(B4:B6) -> 3980
A11: BACKUP FUND SUBTOTAL (earned) | B11: =SUM(B7:B9) -> 600
A13: MONEY OUT
A14: Rent | B14: =Assumptions!$B$10 -> 2100 | D14: Paid through Flex: $1,500 by the 4th, the rest by the 15th
A15: Westlake (due the 17th) | B15: =Assumptions!$B$11 -> 580 | D15: Your paycheck lands the 18th — ONE DAY LATE every month
A16: Daycare | B16: =Assumptions!$B$12 -> 300
A17: Loan Mart | B17: =Assumptions!$B$13 -> 240
A18: Light | B18: =Assumptions!$B$14 -> 200
A19: Spectrum | B19: =Assumptions!$B$15 -> 100 | D19: Safest bill to be late on
A20: Car storage | B20: =Assumptions!$B$16 -> 80
A21: Credit repair | B21: =Assumptions!$B$17 -> 70
A22: Living money ×4 weeks | B22: =Assumptions!$B$18*4 -> 400 | D22: Gas, food, medicine
A23: TOTAL OUT | B23: =SUM(B14:B22) -> 4070
A25: RENT SAVINGS ACCOUNT
A26: Opening balance | B26: =October!B31 -> 450 | D26: Last month's leftover. This is NOT spare money — it is next month's rent arriving early.
A27: + Money in (guaranteed + backup) | B27: =B10+B11 -> 4580
A28: − Money out (rent included) | B28: =B23 -> 4070
A29: CLOSING BALANCE | B29: =B26+B27-B28 -> 960 | D29: Carries into next month as the opening balance
A30: Added this month | B30: =B29-B26 -> 510
A31: Could this pay next month's rent alone? | B31: =IF(B29>=Assumptions!$B$10,"YES","NO — short $"&TEXT(Assumptions!$B$10-B29,"#,##0")) -> NO — short $1,140
A33: IF NO SIDE HUSTLE AT ALL
A34: Closing balance with $0 earned | B34: =B26+B10-B23 -> 360 | D34: The gap between this and the number above is exactly what the side work buys you.

Sheet December
A1: DECEMBER — MONEY IN vs MONEY OUT
A3: MONEY IN
A4: Child Support — Aguayo ×5 Tuesdays | B4: =Assumptions!$B$5*5 -> 1600 | D4: Guaranteed
A5: State paycheck ×2 | B5: =Assumptions!$B$6*2 -> 2200 | D5: Guaranteed
A6: Child Support — Cartagena ×2 | B6: =Assumptions!$B$8*2 -> 500 | D6: Guaranteed
A7: Plasma | B7: =Assumptions!$B$27 -> 200 | D7: MUST BE EARNED
A8: DoorDash / Uber | B8: =Assumptions!$B$28 -> 200 | D8: MUST BE EARNED
A9: Process server | B9: =Assumptions!$B$29*1 -> 200 | D9: MUST BE EARNED
A10: GUARANTEED SUBTOTAL | B10: =SUM(B4:B6) -> 4300
A11: BACKUP FUND SUBTOTAL (earned) | B11: =SUM(B7:B9) -> 600
A13: MONEY OUT
A14: Rent | B14: =Assumptions!$B$10 -> 2100 | D14: Paid through Flex: $1,500 by the 4th, the rest by the 15th
A15: Westlake (due the 17th) | B15: =Assumptions!$B$11 -> 580 | D15: Your paycheck lands the 18th — ONE DAY LATE every month
A16: Daycare | B16: =Assumptions!$B$12 -> 300
A17: Loan Mart | B17: =Assumptions!$B$13 -> 240
A18: Light | B18: =Assumptions!$B$14 -> 200
A19: Spectrum | B19: =Assumptions!$B$15 -> 100 | D19: Safest bill to be late on
A20: Car storage | B20: =Assumptions!$B$16 -> 80
A21: Credit repair | B21: =Assumptions!$B$17 -> 70
A22: Living money ×5 weeks | B22: =Assumptions!$B$18*5 -> 500 | D22: Gas, food, medicine
A23: Holiday spending | B23: =300 -> 300 | D23: Set it in advance so it cannot eat January
A24: TOTAL OUT | B24: =SUM(B14:B23) -> 4470
A26: RENT SAVINGS ACCOUNT
A27: Opening balance | B27: =November!B29 -> 960 | D27: Last month's leftover. This is NOT spare money — it is next month's rent arriving early.
A28: + Money in (guaranteed + backup) | B28: =B10+B11 -> 4900
A29: − Money out (rent included) | B29: =B24 -> 4470
A30: CLOSING BALANCE | B30: =B27+B28-B29 -> 1390 | D30: Carries into next month as the opening balance
A31: Added this month | B31: =B30-B27 -> 430
A32: Could this pay next month's rent alone? | B32: =IF(B30>=Assumptions!$B$10,"YES","NO — short $"&TEXT(Assumptions!$B$10-B30,"#,##0")) -> NO — short $710
A34: IF NO SIDE HUSTLE AT ALL
A35: Closing balance with $0 earned | B35: =B27+B10-B24 -> 790 | D35: The gap between this and the number above is exactly what the side work buys you.
